adsmiff/__init__.py
adsmiff/main.py
adsmiff-0.0.1.dist-info/METADATA
adsmiff-0.0.1.dist-info/WHEEL
adsmiff-0.0.1.dist-info/top_level.txt
adsmiff-0.0.1.dist-info/RECORD
