Metadata-Version: 2.1
Name: adsmiff
Version: 0.0.1
Summary: adsmiff is a Python library tailored for business mathematics.
Author: Jai Madera
Author-email: onesthathumbled@gmail.com
